expedite/__init__.py
expedite/client/__init__.py
expedite/client/auth.py
expedite/client/base.py
expedite/client/bridge/__init__.py
expedite/client/bridge/data.py
expedite/client/bridge/main.py
expedite/client/bridge/room.py
expedite/client/bridge/util.py
expedite/client/bridge/wind.py
expedite/client/conn.py
expedite/client/excp.py
expedite/client/meet.py
expedite/client/prompt/__init__.py
expedite/client/prompt/main.py
expedite/client/prompt/room.py
expedite/client/prompt/util.py
expedite/config/__init__.py
expedite/config/standard.py
expedite/server/__init__.py
expedite/server/base.py
expedite/server/conn.py
expedite/server/main.py
expedite/server/meet.py
expedite/server/room.py
expedite/view.py
expedite-0.1.0.dist-info/LICENSE
expedite-0.1.0.dist-info/METADATA
expedite-0.1.0.dist-info/WHEEL
expedite-0.1.0.dist-info/entry_points.txt
expedite-0.1.0.dist-info/RECORD
